CommPy/__init__.py
CommPy/math.py
CommPy/channelCoding/channels.py
commpy-0.1.1.dist-info/licenses/LICENSE
commpy-0.1.1.dist-info/METADATA
commpy-0.1.1.dist-info/WHEEL
commpy-0.1.1.dist-info/top_level.txt
commpy-0.1.1.dist-info/RECORD
